LICENSE.chromedriver
README.md
cpasm_setup.py
src/cpasm.egg-info/PKG-INFO
src/cpasm.egg-info/SOURCES.txt
src/cpasm.egg-info/dependency_links.txt
src/cpasm.egg-info/top_level.txt