Metadata-Version: 2.1
Name: cpasm
Version: 0.0.0
Summary: Cross Platform Assembly Project
License-File: LICENSE.chromedriver
